SchoolManager/SchoolManager.py
SchoolManager/__init__.py
SchoolManager-1.0.0.dist-info/LICENSE
SchoolManager-1.0.0.dist-info/METADATA
SchoolManager-1.0.0.dist-info/WHEEL
SchoolManager-1.0.0.dist-info/top_level.txt
SchoolManager-1.0.0.dist-info/RECORD
