Metadata-Version: 2.1
Name: SchoolManager
Version: 1.0.0
Summary: this library can use for all user and this is a school manager
Author: Parsa Dehghani
Author-email: <lspd099@gmail.com>
Keywords: School,Manager,Python,Student,Teacher,Class
Classifier: Programming Language :: Python :: 3
Classifier: Programming Language :: Python :: 3.11
Classifier: License :: OSI Approved :: MIT License
Classifier: Operating System :: Microsoft :: Windows :: Windows 10
Classifier: Operating System :: Microsoft :: Windows :: Windows 11
Classifier: Framework :: Django
Classifier: Development Status :: 5 - Production/Stable
Classifier: Intended Audience :: Customer Service
Classifier: Intended Audience :: Developers
Requires-Python: >=3.6
License-File: LICENSE
